buildfast/__init__.py
buildfast-0.1.0.dist-info/licenses/LICENSE
buildfast-0.1.0.dist-info/METADATA
buildfast-0.1.0.dist-info/WHEEL
buildfast-0.1.0.dist-info/top_level.txt
buildfast-0.1.0.dist-info/RECORD
